{
  "name": "YouTuiAdSDKTopOnAdapter",
  "version": "0.1.1",
  "summary": "YouTuiAdSDKTopOnAdapter custom ADN adapter for TPNiOS",
  "description": "TODO: Add long description of the pod here.",
  "homepage": "http://youtui.gameley.com",
  "license": {
    "type": "MIT",
    "file": "LICENSE"
  },
  "authors": {
    "gameley": "dongzhiyue@gameley.com"
  },
  "source": {
    "git": "https://e.coding.net/gameley/youtuiadsdk/YouTuiAdSDKTopOnAdapter.git",
    "tag": "0.1.1"
  },
  "platforms": {
    "ios": "13.0"
  },
  "dependencies": {
    "TPNiOS": [

    ],
    "YouTuiAdSDK": [

    ]
  },
  "static_framework": true,
  "default_subspecs": [
    "Core",
    "BaseAd",
    "SplashAd",
    "RewardVideoAd",
    "InterstitialAd",
    "NativeAd"
  ],
  "subspecs": [
    {
      "name": "Core",
      "source_files": "YouTuiAdSDKTopOnAdapter/Classes/core/**/*"
    },
    {
      "name": "BaseAd",
      "dependencies": {
        "YouTuiAdSDKTopOnAdapter/Core": [

        ]
      },
      "source_files": "YouTuiAdSDKTopOnAdapter/Classes/baseAd/**/*"
    },
    {
      "name": "SplashAd",
      "dependencies": {
        "YouTuiAdSDKTopOnAdapter/Core": [

        ],
        "YouTuiAdSDKTopOnAdapter/BaseAd": [

        ]
      },
      "source_files": "YouTuiAdSDKTopOnAdapter/Classes/splash/**/*"
    },
    {
      "name": "RewardVideoAd",
      "dependencies": {
        "YouTuiAdSDKTopOnAdapter/Core": [

        ],
        "YouTuiAdSDKTopOnAdapter/BaseAd": [

        ]
      },
      "source_files": "YouTuiAdSDKTopOnAdapter/Classes/reward/**/*"
    },
    {
      "name": "InterstitialAd",
      "dependencies": {
        "YouTuiAdSDKTopOnAdapter/Core": [

        ],
        "YouTuiAdSDKTopOnAdapter/BaseAd": [

        ]
      },
      "source_files": "YouTuiAdSDKTopOnAdapter/Classes/interstitial/**/*"
    },
    {
      "name": "NativeAd",
      "dependencies": {
        "YouTuiAdSDKTopOnAdapter/Core": [

        ],
        "YouTuiAdSDKTopOnAdapter/BaseAd": [

        ]
      },
      "source_files": "YouTuiAdSDKTopOnAdapter/Classes/native/**/*"
    }
  ]
}
